Metadata-Version: 2.1
Name: microbarometer
Version: 0.1.0
Summary: Read SEED microbarometer data and plot.
Home-page: https://github.com/scivision/microbarometer
Author: Michael Hirsch, Ph.D.
License: UNKNOWN
Keywords: weather,microbarometer
Platform: UNKNOWN
Classifier: Development Status :: 4 - Beta
Classifier: Environment :: Console
Classifier: Intended Audience :: Science/Research
Classifier: Programming Language :: Python :: 3.6
Classifier: Programming Language :: Python :: 3.7
Classifier: Topic :: Scientific/Engineering :: GIS
Requires-Python: >= 3.6
Provides-Extra: tests
Provides-Extra: plot
Provides-Extra: io
